pypbars/__init__.py
pypbars/pypbars.py
pypbars-0.1.13.dist-info/METADATA
pypbars-0.1.13.dist-info/WHEEL
pypbars-0.1.13.dist-info/namespace_packages.txt
pypbars-0.1.13.dist-info/top_level.txt
pypbars-0.1.13.dist-info/zip-safe
pypbars-0.1.13.dist-info/RECORD
