Metadata-Version: 2.1
Name: pypbars
Version: 0.1.13
Summary: Provides a convenient way to display progress bars for concurrent asyncio or multiprocessing Pool processes.
Home-page: https://github.com/soda480/pypbars
Author: Emilio Reyes
Author-email: soda480@gmail.com
Maintainer: 
Maintainer-email: 
License: Apache License, Version 2.0
Classifier: Programming Language :: Python
Classifier: Programming Language :: Python :: 3.7
Classifier: Programming Language :: Python :: 3.8
Classifier: Programming Language :: Python :: 3.9
Classifier: Programming Language :: Python :: 3.10
Requires-Dist: list2term (~=0.1.5)
Requires-Dist: progress1bar (~=0.3.0)
